setup.cfg
setup.py
add_get_param/__init__.py
add_get_param/templatetags/__init__.py
add_get_param/templatetags/add_get_parameter.py
django_add_get_parameters.egg-info/PKG-INFO
django_add_get_parameters.egg-info/SOURCES.txt
django_add_get_parameters.egg-info/dependency_links.txt
django_add_get_parameters.egg-info/not-zip-safe
django_add_get_parameters.egg-info/top_level.txt