Metadata-Version: 1.1
Name: django-add-get-parameters
Version: 0.4
Summary: Template tag to add get parameter to the current url.
Home-page: http://github.com/RobinRamael/django-add-get-parameters
Author: Robin Ramael
Author-email: robin.ramael@gmail.com
License: UNKNOWN
Platform: UNKNOWN
Classifier: Development Status :: 3 - Alpha
Classifier: Environment :: Web Environment
Classifier: Intended Audience :: Developers
Classifier: License :: OSI Approved :: MIT License
Classifier: Operating System :: OS Independent
Classifier: Programming Language :: Python
Classifier: Framework :: Django
